setup.py
clearnlp/__init__.py
clearnlp/converter.py
clearnlp/ext/args4j-2.0.29.jar
clearnlp/ext/clearnlp-3.1.2.jar
clearnlp/ext/clearnlp-dictionary-3.2.jar
clearnlp/ext/clearnlp-global-lexica-3.1.jar
clearnlp/ext/headrule_en_stanford.txt
clearnlp/ext/hppc-0.6.1.jar
clearnlp/ext/log4j-1.2.17.jar
clearnlp/ext/urls.txt
clearnlp/ext/xz-1.5.jar
clearnlp/tests/__init__.py
clearnlp/tests/test_converter.py
clearnlp_converter.egg-info/PKG-INFO
clearnlp_converter.egg-info/SOURCES.txt
clearnlp_converter.egg-info/dependency_links.txt
clearnlp_converter.egg-info/top_level.txt