Metadata-Version: 1.1
Name: clearnlp-converter
Version: 0.1
Summary: A Python wrapper for Jin-ho Choi's ClearNLP constituency-to-dependency converter.
Home-page: http://github.com/honnibal/py-clearnlp-converter
Author: Matthew Honnibal
Author-email: honnibal@gmail.com
License: UNKNOWN
Platform: UNKNOWN
Classifier: Environment :: Console
Classifier: Operating System :: OS Independent
Classifier: Intended Audience :: Science/Research
Classifier: Programming Language :: Python
Classifier: Topic :: Scientific/Engineering
